LICENSE
README.md
changelog.md
pyproject.toml
renderer/README.md
renderer/__init__.py
renderer/_backport.py
renderer/_meta_utils.py
renderer/geometry.py
renderer/model.py
renderer/pipeline.py
renderer/renderer.py
renderer/scene.py
renderer/shader.py
renderer/shaders/README.md
renderer/shaders/depth.py
renderer/shaders/gouraud.py
renderer/shaders/gouraud_texture.py
renderer/shaders/phong.py
renderer/shaders/phong_darboux.py
renderer/shaders/phong_reflection.py
renderer/shaders/phong_reflection_shadow.py
renderer/shadow.py
renderer/shapes/capsule.py
renderer/shapes/cube.py
renderer/types.py
renderer/utils.py
renderer/value_checker.py
jaxrenderer-0.3.2.dist-info/LICENSE
jaxrenderer-0.3.2.dist-info/METADATA
jaxrenderer-0.3.2.dist-info/WHEEL
jaxrenderer-0.3.2.dist-info/RECORD
