Metadata-Version: 2.1
Name: jaxrenderer
Version: 0.3.2
Summary: Jax implementation of rasterizer renderer.
Home-page: https://github.com/JoeyTeng/jaxrenderer
License: Apache-2.0
Author: Joey Teng
Author-email: joey.teng.dev@gmail.com
Requires-Python: >=3.8,<4.0
Classifier: Development Status :: 3 - Alpha
Classifier: Intended Audience :: Developers
Classifier: Intended Audience :: Education
Classifier: Intended Audience :: Science/Research
Classifier: License :: OSI Approved :: Apache Software License
Classifier: Natural Language :: Chinese (Simplified)
Classifier: Natural Language :: English
Classifier: Operating System :: OS Independent
Classifier: Programming Language :: Python :: 3
Classifier: Programming Language :: Python :: 3.8
Classifier: Programming Language :: Python :: 3.9
Classifier: Programming Language :: Python :: 3.10
Classifier: Programming Language :: Python :: 3.11
Classifier: Topic :: Multimedia :: Graphics :: 3D Rendering
Classifier: Topic :: Scientific/Engineering :: Artificial Intelligence
Classifier: Topic :: Scientific/Engineering :: Visualization
Classifier: Typing :: Typed
Requires-Dist: importlib-metadata (>=6.6.0,<7.0.0)
Requires-Dist: jax (>=0.4.0,<0.5.0)
Requires-Dist: jaxlib (>=0.4.0,<0.5.0)
Requires-Dist: jaxtyping (>=0.2.13,<0.2.20) ; python_version >= "3.8" and python_version < "3.9"
Requires-Dist: jaxtyping (>=0.2.19,<0.3.0) ; python_version >= "3.9" and python_version < "4.0"
Requires-Dist: numpy (>=1.22.0,<2.0.0)
Requires-Dist: typing_extensions (>=4.3.0,<5.0.0)
Project-URL: Bug Tracker, https://github.com/JoeyTeng/jaxrenderer/issues
Project-URL: Repository, https://github.com/JoeyTeng/jaxrenderer
